clap/__init__.py
clap/_core.py
clap/py.typed
python_clap-0.5.0.dist-info/METADATA
python_clap-0.5.0.dist-info/WHEEL
python_clap-0.5.0.dist-info/top_level.txt
python_clap-0.5.0.dist-info/RECORD
