Metadata-Version: 2.1
Name: python-clap
Version: 0.5.0
Summary: (C)ommand (L)ine (A)rgument (P)arsing... A thin wrapper around the standard Python argparse library.
Home-page: https://github.com/bbugyi200/clap
Author: Bryan M Bugyi
Author-email: bryanbugyi34@gmail.com
License: MIT license
Platform: UNKNOWN
Classifier: Development Status :: 3 - Alpha
Classifier: Intended Audience :: Developers
Classifier: License :: OSI Approved :: MIT License
Classifier: Natural Language :: English
Classifier: Programming Language :: Python :: 3
Classifier: Programming Language :: Python :: 3.8
Classifier: Programming Language :: Python :: 3.9
Classifier: Programming Language :: Python :: 3.10
Requires-Python: >=3.8
Requires-Dist: bugyi.lib (~=0.11)
Requires-Dist: pydantic (~=1.8)
Requires-Dist: python-logrus (~=0.1)
